{
  "lastUpdated": "2026-04-30",
  "formatScores": {
    "poll": 0,
    "pick": 9.3,
    "humor": 0,
    "humor-tweet": 0,
    "budget": 6.6,
    "versus": 0,
    "avantapres": 5.3,
    "month": 0,
    "cost-vs": 0,
    "leaderboard": 0,
    "best-time": 0
  },
  "killedFormats": [
    "poll",
    "versus"
  ],
  "destinationScores": {
    "vietnam": 7,
    "chiang mai": 5.6,
    "bali": 5,
    "bangkok": 5,
    "thailande": 4,
    "philippines": 3.4,
    "koh samui": 3,
    "malaisie": 2.7,
    "lombok": 0.8,
    "singapour": 0.8,
    "indonesie": 0.5,
    "phuket": 0.4,
    "cambodge": 0.1
  },
  "recommendations": [
    "bali content trending — prioritize",
    "thailande content trending — prioritize",
    "vietnam content trending — prioritize",
    "Top TikTok format: pick (avg 9.3, 2 videos)"
  ],
  "igFormatScores": {
    "poll": 0,
    "pick": 0,
    "humor": 0,
    "humor-tweet": 0,
    "budget": 0,
    "versus": 0,
    "avantapres": 0,
    "month": 0,
    "cost-vs": 0,
    "leaderboard": 0,
    "best-time": 0
  },
  "tiktokFormatScores": {
    "budget": 6.6,
    "avantapres": 5.3,
    "pick": 9.3
  },
  "formatScoreSource": {
    "pick": "tiktok-only",
    "budget": "tiktok-only",
    "avantapres": "tiktok-only"
  },
  "igDestinationScores": {
    "bali": 7.9,
    "thailande": 4,
    "vietnam": 3.6,
    "bangkok": 3.4,
    "chiang mai": 3.4,
    "koh samui": 3,
    "philippines": 1.8,
    "lombok": 0.8,
    "singapour": 0.8,
    "indonesie": 0.5,
    "malaisie": 0.4,
    "phuket": 0.4,
    "cambodge": 0.1
  },
  "tiktokDestinationScores": {
    "bali": 3,
    "philippines": 4.4,
    "malaisie": 4.2,
    "chiang mai": 7,
    "bangkok": 6.1,
    "vietnam": 9.2
  },
  "destinationScoreSource": {
    "bali": "merged(60/40)",
    "thailande": "ig-only",
    "vietnam": "merged(60/40)",
    "bangkok": "merged(60/40)",
    "chiang mai": "merged(60/40)",
    "koh samui": "ig-only",
    "philippines": "merged(60/40)",
    "lombok": "ig-only",
    "singapour": "ig-only",
    "indonesie": "ig-only",
    "malaisie": "merged(60/40)",
    "phuket": "ig-only",
    "cambodge": "ig-only"
  },
  "mergeConfig": {
    "tiktokWeight": 0.6,
    "igWeight": 0.4,
    "active": true,
    "tiktokVideoCount": 15,
    "tiktokUnclassifiedCount": 3
  }
}