{
  "generatedAt": "2026-06-30T12:41:25.540Z",
  "totalTopics": 2,
  "byAction": {
    "publish_now": 0,
    "queue_priority": 0,
    "queue_normal": 2
  },
  "queue": [
    {
      "topic": "Finnish fugitive wanted through Interpol arrested in Bangkok",
      "source": "rss_breaking",
      "destination": "thailand",
      "link": "https://thethaiger.com/news/national/finnish-fugitive-arrested-bangkok",
      "velocityScore": 0.489,
      "action": "QUEUE_NORMAL",
      "hoursRemaining": 718,
      "topicType": {
        "key": "evergreen_trend",
        "halfLifeHours": 720
      },
      "estimatedTrafficNow": 2445,
      "estimatedTrafficIn24h": 2389,
      "trafficLossPerHour": 2,
      "breakdown": {
        "trendIntensity": 0.98,
        "timeDecay": 0.998,
        "competitionGap": 0.5,
        "monetizationBoost": 1,
        "hoursSinceDetection": 2.3
      },
      "detectedAt": "2026-06-30T10:25:25.000Z",
      "scoredAt": "2026-06-30T12:41:18.397Z"
    },
    {
      "topic": "Mother accuses immigration of separating her from her children",
      "source": "rss_breaking",
      "destination": "thailand",
      "link": "https://thethaiger.com/news/bangkok/mother-says-her-thai-chinese-children-denied-entry-to-thailand",
      "velocityScore": 0.448,
      "action": "QUEUE_NORMAL",
      "hoursRemaining": 716,
      "topicType": {
        "key": "evergreen_trend",
        "halfLifeHours": 720
      },
      "estimatedTrafficNow": 2242,
      "estimatedTrafficIn24h": 2191,
      "trafficLossPerHour": 2,
      "breakdown": {
        "trendIntensity": 0.9,
        "timeDecay": 0.997,
        "competitionGap": 0.5,
        "monetizationBoost": 1,
        "hoursSinceDetection": 3.6
      },
      "detectedAt": "2026-06-30T09:04:19.000Z",
      "scoredAt": "2026-06-30T12:41:19.812Z"
    }
  ]
}