{
  "timestamp": "2026-04-12T05:32:37.746Z",
  "competitors": [
    {
      "id": "voyagespirates",
      "name": "VoyagesPirates",
      "totalUrls": 0,
      "newUrls": 0
    },
    {
      "id": "noobvoyage",
      "name": "Noobvoyage",
      "totalUrls": 126,
      "newUrls": 0
    },
    {
      "id": "generationvoyage",
      "name": "Generation Voyage",
      "totalUrls": 4407,
      "newUrls": 1001
    }
  ],
  "newArticles": [
    {
      "competitor": "generationvoyage",
      "url": "https://generationvoyage.fr/treks-nepal/",
      "lastmod": "2025-12-16T17:57:04+00:00",
      "destination": "nepal",
      "contentType": "general",
      "title": "Treks Nepal",
      "action": "content_gap",
      "priority": "P1",
      "reason": "Competitor covers \"Treks Nepal\" (nepal, general) — no matching FlashVoyage article found"
    },
    {
      "competitor": "generationvoyage",
      "url": "https://generationvoyage.fr/visiter-siem-reap-faire-voir/",
      "lastmod": "2025-12-16T18:32:13+00:00",
      "destination": "siem-reap",
      "contentType": "activites",
      "title": "Visiter Siem Reap Faire Voir",
      "action": "content_gap",
      "priority": "P1",
      "reason": "Competitor covers \"Visiter Siem Reap Faire Voir\" (siem-reap, activites) — no matching FlashVoyage article found"
    },
    {
      "competitor": "generationvoyage",
      "url": "https://generationvoyage.fr/endroits-visiter-inde/",
      "lastmod": "2025-12-16T18:36:10+00:00",
      "destination": "inde",
      "contentType": "activites",
      "title": "Endroits Visiter Inde",
      "action": "content_gap",
      "priority": "P1",
      "reason": "Competitor covers \"Endroits Visiter Inde\" (inde, activites) — no matching FlashVoyage article found"
    },
    {
      "competitor": "generationvoyage",
      "url": "https://generationvoyage.fr/jardin-zen-kyoto/",
      "lastmod": "2025-12-24T09:01:11+00:00",
      "destination": "kyoto",
      "contentType": "general",
      "title": "Jardin Zen Kyoto",
      "action": "content_gap",
      "priority": "P1",
      "reason": "Competitor covers \"Jardin Zen Kyoto\" (kyoto, general) — no matching FlashVoyage article found"
    },
    {
      "competitor": "generationvoyage",
      "url": "https://generationvoyage.fr/temple-kyoto/",
      "lastmod": "2025-12-24T09:36:19+00:00",
      "destination": "kyoto",
      "contentType": "activites",
      "title": "Temple Kyoto",
      "action": "content_gap",
      "priority": "P1",
      "reason": "Competitor covers \"Temple Kyoto\" (kyoto, activites) — no matching FlashVoyage article found"
    },
    {
      "competitor": "generationvoyage",
      "url": "https://generationvoyage.fr/9-choses-a-faire-a-kyoto/",
      "lastmod": "2025-12-24T10:02:41+00:00",
      "destination": "kyoto",
      "contentType": "general",
      "title": "9 Choses A Faire A Kyoto",
      "action": "content_gap",
      "priority": "P1",
      "reason": "Competitor covers \"9 Choses A Faire A Kyoto\" (kyoto, general) — no matching FlashVoyage article found"
    },
    {
      "competitor": "generationvoyage",
      "url": "https://generationvoyage.fr/visiter-phuket-faire-voir/",
      "lastmod": "2025-12-24T10:03:51+00:00",
      "destination": "phuket",
      "contentType": "activites",
      "title": "Visiter Phuket Faire Voir",
      "action": "content_gap",
      "priority": "P1",
      "reason": "Competitor covers \"Visiter Phuket Faire Voir\" (phuket, activites) — no matching FlashVoyage article found"
    },
    {
      "competitor": "generationvoyage",
      "url": "https://generationvoyage.fr/spots-plongee-philippines/",
      "lastmod": "2025-12-16T16:40:17+00:00",
      "destination": "philippines",
      "contentType": "plage",
      "title": "Spots Plongee Philippines",
      "action": "monitor",
      "priority": "P3",
      "reason": "We cover this topic: \"eSIM Philippines : Globe vs Smart, le comparatif que personne ne fait\" (score=37, freshness=1.00)",
      "matchedArticle": {
        "wpId": 4372,
        "slug": "esim-philippines-globe-smart-comparatif-2026",
        "compositeScore": 37,
        "freshness": 1
      }
    },
    {
      "competitor": "generationvoyage",
      "url": "https://generationvoyage.fr/plus-belles-iles-philippines/",
      "lastmod": "2025-12-16T16:43:38+00:00",
      "destination": "philippines",
      "contentType": "plage",
      "title": "Plus Belles Iles Philippines",
      "action": "monitor",
      "priority": "P3",
      "reason": "We cover this topic: \"eSIM Philippines : Globe vs Smart, le comparatif que personne ne fait\" (score=37, freshness=1.00)",
      "matchedArticle": {
        "wpId": 4372,
        "slug": "esim-philippines-globe-smart-comparatif-2026",
        "compositeScore": 37,
        "freshness": 1
      }
    },
    {
      "competitor": "generationvoyage",
      "url": "https://generationvoyage.fr/riziere-philippines/",
      "lastmod": "2025-12-16T16:44:12+00:00",
      "destination": "philippines",
      "contentType": "general",
      "title": "Riziere Philippines",
      "action": "monitor",
      "priority": "P3",
      "reason": "We cover this topic: \"eSIM Philippines : Globe vs Smart, le comparatif que personne ne fait\" (score=37, freshness=1.00)",
      "matchedArticle": {
        "wpId": 4372,
        "slug": "esim-philippines-globe-smart-comparatif-2026",
        "compositeScore": 37,
        "freshness": 1
      }
    },
    {
      "competitor": "generationvoyage",
      "url": "https://generationvoyage.fr/island-hopping-philippines/",
      "lastmod": "2025-12-16T16:45:40+00:00",
      "destination": "philippines",
      "contentType": "general",
      "title": "Island Hopping Philippines",
      "action": "monitor",
      "priority": "P3",
      "reason": "We cover this topic: \"eSIM Philippines : Globe vs Smart, le comparatif que personne ne fait\" (score=37, freshness=1.00)",
      "matchedArticle": {
        "wpId": 4372,
        "slug": "esim-philippines-globe-smart-comparatif-2026",
        "compositeScore": 37,
        "freshness": 1
      }
    },
    {
      "competitor": "generationvoyage",
      "url": "https://generationvoyage.fr/surf-bali/",
      "lastmod": "2025-12-16T17:08:58+00:00",
      "destination": "bali",
      "contentType": "general",
      "title": "Surf Bali",
      "action": "monitor",
      "priority": "P3",
      "reason": "We cover this topic: \"Bali + Lombok + Gili en 10 jours : l’itinéraire budget que les blogs te cachent\" (score=34, freshness=1.00)",
      "matchedArticle": {
        "wpId": 4370,
        "slug": "bali-lombok-gili-10-jours-itineraire-budget-2026",
        "compositeScore": 34,
        "freshness": 1
      }
    },
    {
      "competitor": "generationvoyage",
      "url": "https://generationvoyage.fr/randonnee-mont-batur-bali/",
      "lastmod": "2025-12-16T17:16:24+00:00",
      "destination": "bali",
      "contentType": "general",
      "title": "Randonnee Mont Batur Bali",
      "action": "monitor",
      "priority": "P3",
      "reason": "We cover this topic: \"Bali + Lombok + Gili en 10 jours : l’itinéraire budget que les blogs te cachent\" (score=34, freshness=1.00)",
      "matchedArticle": {
        "wpId": 4370,
        "slug": "bali-lombok-gili-10-jours-itineraire-budget-2026",
        "compositeScore": 34,
        "freshness": 1
      }
    },
    {
      "competitor": "generationvoyage",
      "url": "https://generationvoyage.fr/visiter-cascade-tegenungan-bali/",
      "lastmod": "2025-12-16T17:34:42+00:00",
      "destination": "bali",
      "contentType": "activites",
      "title": "Visiter Cascade Tegenungan Bali",
      "action": "monitor",
      "priority": "P3",
      "reason": "We cover this topic: \"Bali + Lombok + Gili en 10 jours : l’itinéraire budget que les blogs te cachent\" (score=34, freshness=1.00)",
      "matchedArticle": {
        "wpId": 4370,
        "slug": "bali-lombok-gili-10-jours-itineraire-budget-2026",
        "compositeScore": 34,
        "freshness": 1
      }
    },
    {
      "competitor": "generationvoyage",
      "url": "https://generationvoyage.fr/visiter-lombok-faire-voir/",
      "lastmod": "2025-12-16T17:45:55+00:00",
      "destination": "lombok",
      "contentType": "activites",
      "title": "Visiter Lombok Faire Voir",
      "action": "monitor",
      "priority": "P3",
      "reason": "We cover this topic: \"Vivre à Lombok en tant que nomade numérique : les 10 coûts cachés qui dévorent ton budget\" (score=15, freshness=1.00)",
      "matchedArticle": {
        "wpId": 3251,
        "slug": "vivre-a-lombok-en-tant-que-nomade-numerique-les-10-couts-caches-qui-devorent-ton-budget",
        "compositeScore": 15,
        "freshness": 1
      }
    },
    {
      "competitor": "generationvoyage",
      "url": "https://generationvoyage.fr/visiter-kuala-lumpur-faire-voir/",
      "lastmod": "2025-12-16T18:27:13+00:00",
      "destination": "kuala-lumpur",
      "contentType": "activites",
      "title": "Visiter Kuala Lumpur Faire Voir",
      "action": "monitor",
      "priority": "P3",
      "reason": "We cover this topic: \"Choisir Entre Taipei et Kuala Lumpur : Un Itinéraire de 4 Jours Qui Compte\" (score=14, freshness=0.95)",
      "matchedArticle": {
        "wpId": 2980,
        "slug": "choisir-entre-taipei-et-kuala-lumpur-un-itineraire-de-4-jours-qui-compte",
        "compositeScore": 14,
        "freshness": 0.95
      }
    },
    {
      "competitor": "generationvoyage",
      "url": "https://generationvoyage.fr/endroits-visiter-malaisie/",
      "lastmod": "2025-12-16T18:27:19+00:00",
      "destination": "malaisie",
      "contentType": "activites",
      "title": "Endroits Visiter Malaisie",
      "action": "monitor",
      "priority": "P3",
      "reason": "We cover this topic: \"Malaisie : escale à Singapour ou Kuala Lumpur, quel choix privilégier ?\" (score=22, freshness=1.00)",
      "matchedArticle": {
        "wpId": 5189,
        "slug": "malaisie-escale-a-singapour-ou-kuala-lumpur-quel-choix-privilegier",
        "compositeScore": 22,
        "freshness": 1
      }
    },
    {
      "competitor": "generationvoyage",
      "url": "https://generationvoyage.fr/visiter-singapour-faire-voir/",
      "lastmod": "2025-12-16T18:28:15+00:00",
      "destination": "singapour",
      "contentType": "activites",
      "title": "Visiter Singapour Faire Voir",
      "action": "monitor",
      "priority": "P3",
      "reason": "We cover this topic: \"Kuala Lumpur ou Singapour : quel stopover optimisera vraiment ton voyage ?\" (score=32, freshness=1.00)",
      "matchedArticle": {
        "wpId": 5072,
        "slug": "kuala-lumpur-ou-singapour-quel-stopover-optimisera-vraiment-ton-voyage",
        "compositeScore": 32,
        "freshness": 1
      }
    },
    {
      "competitor": "generationvoyage",
      "url": "https://generationvoyage.fr/endroits-visiter-cambodge/",
      "lastmod": "2025-12-16T18:32:22+00:00",
      "destination": "cambodge",
      "contentType": "activites",
      "title": "Endroits Visiter Cambodge",
      "action": "monitor",
      "priority": "P3",
      "reason": "We cover this topic: \"Visa Cambodge 2026 : e-visa, prix, pièges et ce que les sites officiels ne disent pas\" (score=43, freshness=1.00)",
      "matchedArticle": {
        "wpId": 4369,
        "slug": "visa-cambodge-francais-2026-evisa-prix-pieges",
        "compositeScore": 43,
        "freshness": 1
      }
    },
    {
      "competitor": "generationvoyage",
      "url": "https://generationvoyage.fr/guide-quartier-lumphini-bangkok/",
      "lastmod": "2025-12-19T14:03:49+00:00",
      "destination": "bangkok",
      "contentType": "guide",
      "title": "Guide Quartier Lumphini Bangkok",
      "action": "monitor",
      "priority": "P3",
      "reason": "We cover this topic: \"Choisir entre Bangkok et Chiang Mai : Le Dilemme Logistique des Nomades\" (score=15, freshness=0.98)",
      "matchedArticle": {
        "wpId": 3174,
        "slug": "choisir-entre-bangkok-et-chiang-mai-le-dilemme-logistique-des-nomades",
        "compositeScore": 15,
        "freshness": 0.98
      }
    },
    {
      "competitor": "generationvoyage",
      "url": "https://generationvoyage.fr/endroits-visiter-vietnam/",
      "lastmod": "2025-12-19T14:21:27+00:00",
      "destination": "vietnam",
      "contentType": "activites",
      "title": "Endroits Visiter Vietnam",
      "action": "monitor",
      "priority": "P3",
      "reason": "We cover this topic: \"eSIM Vietnam : le comparatif que les blogs ne font jamais (et les frais cachés)\" (score=52, freshness=1.00)",
      "matchedArticle": {
        "wpId": 4250,
        "slug": "esim-vietnam-comparatif-forfait-2026-frais-caches",
        "compositeScore": 52,
        "freshness": 1
      }
    },
    {
      "competitor": "generationvoyage",
      "url": "https://generationvoyage.fr/plus-beaux-endroits-philippines/",
      "lastmod": "2025-12-19T14:25:10+00:00",
      "destination": "philippines",
      "contentType": "general",
      "title": "Plus Beaux Endroits Philippines",
      "action": "monitor",
      "priority": "P3",
      "reason": "We cover this topic: \"eSIM Philippines : Globe vs Smart, le comparatif que personne ne fait\" (score=37, freshness=1.00)",
      "matchedArticle": {
        "wpId": 4372,
        "slug": "esim-philippines-globe-smart-comparatif-2026",
        "compositeScore": 37,
        "freshness": 1
      }
    },
    {
      "competitor": "generationvoyage",
      "url": "https://generationvoyage.fr/temples-bali/",
      "lastmod": "2025-12-19T14:26:11+00:00",
      "destination": "bali",
      "contentType": "activites",
      "title": "Temples Bali",
      "action": "monitor",
      "priority": "P3",
      "reason": "We cover this topic: \"Bali + Lombok + Gili en 10 jours : l’itinéraire budget que les blogs te cachent\" (score=34, freshness=1.00)",
      "matchedArticle": {
        "wpId": 4370,
        "slug": "bali-lombok-gili-10-jours-itineraire-budget-2026",
        "compositeScore": 34,
        "freshness": 1
      }
    },
    {
      "competitor": "generationvoyage",
      "url": "https://generationvoyage.fr/guide-quartier-hua-lamphong-bangkok/",
      "lastmod": "2025-12-19T14:30:17+00:00",
      "destination": "bangkok",
      "contentType": "guide",
      "title": "Guide Quartier Hua Lamphong Bangkok",
      "action": "monitor",
      "priority": "P3",
      "reason": "We cover this topic: \"Choisir entre Bangkok et Chiang Mai : Le Dilemme Logistique des Nomades\" (score=15, freshness=0.98)",
      "matchedArticle": {
        "wpId": 3174,
        "slug": "choisir-entre-bangkok-et-chiang-mai-le-dilemme-logistique-des-nomades",
        "compositeScore": 15,
        "freshness": 0.98
      }
    },
    {
      "competitor": "generationvoyage",
      "url": "https://generationvoyage.fr/temples-et-palais-tokyo/",
      "lastmod": "2025-12-19T16:38:10+00:00",
      "destination": "tokyo",
      "contentType": "activites",
      "title": "Temples Et Palais Tokyo",
      "action": "monitor",
      "priority": "P3",
      "reason": "We cover this topic: \"Entre Hong Kong et Tokyo : Choix Cruciaux pour un Itinéraire Parfait\" (score=15, freshness=0.97)",
      "matchedArticle": {
        "wpId": 3048,
        "slug": "entre-hong-kong-et-tokyo-choix-cruciaux-pour-un-itineraire-parfait",
        "compositeScore": 15,
        "freshness": 0.97
      }
    },
    {
      "competitor": "generationvoyage",
      "url": "https://generationvoyage.fr/lieux-samourais-tokyo/",
      "lastmod": "2025-12-19T16:39:16+00:00",
      "destination": "tokyo",
      "contentType": "general",
      "title": "Lieux Samourais Tokyo",
      "action": "monitor",
      "priority": "P3",
      "reason": "We cover this topic: \"Entre Hong Kong et Tokyo : Choix Cruciaux pour un Itinéraire Parfait\" (score=15, freshness=0.97)",
      "matchedArticle": {
        "wpId": 3048,
        "slug": "entre-hong-kong-et-tokyo-choix-cruciaux-pour-un-itineraire-parfait",
        "compositeScore": 15,
        "freshness": 0.97
      }
    },
    {
      "competitor": "generationvoyage",
      "url": "https://generationvoyage.fr/excursion-tokyo/",
      "lastmod": "2025-12-19T16:40:02+00:00",
      "destination": "tokyo",
      "contentType": "general",
      "title": "Excursion Tokyo",
      "action": "monitor",
      "priority": "P3",
      "reason": "We cover this topic: \"Entre Hong Kong et Tokyo : Choix Cruciaux pour un Itinéraire Parfait\" (score=15, freshness=0.97)",
      "matchedArticle": {
        "wpId": 3048,
        "slug": "entre-hong-kong-et-tokyo-choix-cruciaux-pour-un-itineraire-parfait",
        "compositeScore": 15,
        "freshness": 0.97
      }
    },
    {
      "competitor": "generationvoyage",
      "url": "https://generationvoyage.fr/temple-japonais-visiter/",
      "lastmod": "2025-12-24T09:36:26+00:00",
      "destination": "japon",
      "contentType": "activites",
      "title": "Temple Japonais Visiter",
      "action": "monitor",
      "priority": "P3",
      "reason": "We cover this topic: \"Japon en couple 15 jours : budget tout compris et les frais que personne ne mentionne\" (score=46, freshness=1.00)",
      "matchedArticle": {
        "wpId": 4373,
        "slug": "japon-couple-15-jours-budget-tout-compris-2026",
        "compositeScore": 46,
        "freshness": 1
      }
    },
    {
      "competitor": "generationvoyage",
      "url": "https://generationvoyage.fr/endroits-fan-manga-japon/",
      "lastmod": "2025-12-24T09:36:30+00:00",
      "destination": "japon",
      "contentType": "general",
      "title": "Endroits Fan Manga Japon",
      "action": "monitor",
      "priority": "P3",
      "reason": "We cover this topic: \"Japon en couple 15 jours : budget tout compris et les frais que personne ne mentionne\" (score=46, freshness=1.00)",
      "matchedArticle": {
        "wpId": 4373,
        "slug": "japon-couple-15-jours-budget-tout-compris-2026",
        "compositeScore": 46,
        "freshness": 1
      }
    },
    {
      "competitor": "generationvoyage",
      "url": "https://generationvoyage.fr/plages-philippines/",
      "lastmod": "2025-12-24T10:01:39+00:00",
      "destination": "philippines",
      "contentType": "plage",
      "title": "Plages Philippines",
      "action": "monitor",
      "priority": "P3",
      "reason": "We cover this topic: \"eSIM Philippines : Globe vs Smart, le comparatif que personne ne fait\" (score=37, freshness=1.00)",
      "matchedArticle": {
        "wpId": 4372,
        "slug": "esim-philippines-globe-smart-comparatif-2026",
        "compositeScore": 37,
        "freshness": 1
      }
    },
    {
      "competitor": "generationvoyage",
      "url": "https://generationvoyage.fr/randonnees-philippines/",
      "lastmod": "2025-12-24T10:01:44+00:00",
      "destination": "philippines",
      "contentType": "general",
      "title": "Randonnees Philippines",
      "action": "monitor",
      "priority": "P3",
      "reason": "We cover this topic: \"eSIM Philippines : Globe vs Smart, le comparatif que personne ne fait\" (score=37, freshness=1.00)",
      "matchedArticle": {
        "wpId": 4372,
        "slug": "esim-philippines-globe-smart-comparatif-2026",
        "compositeScore": 37,
        "freshness": 1
      }
    },
    {
      "competitor": "generationvoyage",
      "url": "https://generationvoyage.fr/ascension-volcans-philippines/",
      "lastmod": "2025-12-24T10:01:50+00:00",
      "destination": "philippines",
      "contentType": "transport",
      "title": "Ascension Volcans Philippines",
      "action": "monitor",
      "priority": "P3",
      "reason": "We cover this topic: \"eSIM Philippines : Globe vs Smart, le comparatif que personne ne fait\" (score=37, freshness=1.00)",
      "matchedArticle": {
        "wpId": 4372,
        "slug": "esim-philippines-globe-smart-comparatif-2026",
        "compositeScore": 37,
        "freshness": 1
      }
    },
    {
      "competitor": "generationvoyage",
      "url": "https://generationvoyage.fr/cascades-philippines/",
      "lastmod": "2025-12-24T10:01:53+00:00",
      "destination": "philippines",
      "contentType": "general",
      "title": "Cascades Philippines",
      "action": "monitor",
      "priority": "P3",
      "reason": "We cover this topic: \"eSIM Philippines : Globe vs Smart, le comparatif que personne ne fait\" (score=37, freshness=1.00)",
      "matchedArticle": {
        "wpId": 4372,
        "slug": "esim-philippines-globe-smart-comparatif-2026",
        "compositeScore": 37,
        "freshness": 1
      }
    },
    {
      "competitor": "generationvoyage",
      "url": "https://generationvoyage.fr/activites-famille-philippines/",
      "lastmod": "2025-12-24T10:01:56+00:00",
      "destination": "philippines",
      "contentType": "activites",
      "title": "Activites Famille Philippines",
      "action": "monitor",
      "priority": "P3",
      "reason": "We cover this topic: \"eSIM Philippines : Globe vs Smart, le comparatif que personne ne fait\" (score=37, freshness=1.00)",
      "matchedArticle": {
        "wpId": 4372,
        "slug": "esim-philippines-globe-smart-comparatif-2026",
        "compositeScore": 37,
        "freshness": 1
      }
    }
  ],
  "summary": {
    "totalNew": 34,
    "contentGaps": 7,
    "staleRefreshes": 0,
    "monitoring": 27
  }
}